bvlain/__init__.py
bvlain/_version.py
bvlain/cli.py
bvlain/core.py
bvlain/potentials.py
bvlain/data/__init__.py
bvlain/data/anion.pkl
bvlain/data/cation.pkl
bvlain/data/covalent_radii.py
bvlain/data/covalent_radii_softvb.pkl
bvlain/data/quantum_n.pkl
bvlain/data/shannon-radii.json
bvlain-0.25.1.dist-info/LICENSE
bvlain-0.25.1.dist-info/METADATA
bvlain-0.25.1.dist-info/WHEEL
bvlain-0.25.1.dist-info/top_level.txt
bvlain-0.25.1.dist-info/RECORD
