Metadata-Version: 2.1
Name: bvlain
Version: 0.25.1
Summary: The Bond valence site energy calculator
Home-page: https://github.com/dembart/BVlain
Author: Artem Dembitskiy
Author-email: art.dembitskiy@gmail.com
License: UNKNOWN
Platform: UNKNOWN
Classifier: Programming Language :: Python :: 3.8
Classifier: Programming Language :: Python :: 3.9
Classifier: Programming Language :: Python :: 3.10
Classifier: Programming Language :: Python :: 3.11
Classifier: Programming Language :: Python :: 3.12
Classifier: License :: OSI Approved :: MIT License
Classifier: Operating System :: OS Independent
License-File: LICENSE
Requires-Dist: numpy
Requires-Dist: pandas
Requires-Dist: scipy (>=1.7.0)
Requires-Dist: pymatgen (>=2022.5.26)
Requires-Dist: ase
Requires-Dist: joblib
